[
    {
        "nombre": "yaiiua",
        "puntuacion": 35,
        "hora": "2024-12-03 12:22:24"
    },
    {
        "nombre": null,
        "puntuacion": 35,
        "hora": "2024-12-03 12:22:27"
    },
    {
        "nombre": "yamila",
        "puntuacion": 25,
        "hora": "2024-12-03 11:31:24"
    },
    {
        "nombre": "nhnhkhjkhjkhjkshkshjks",
        "puntuacion": 25,
        "hora": "2024-12-03 11:31:31"
    },
    {
        "nombre": "yamilal",
        "puntuacion": 15,
        "hora": "2024-12-03 13:39:51"
    },
    {
        "nombre": "",
        "puntuacion": 15,
        "hora": "2024-12-03 13:39:56"
    },
    {
        "nombre": "jhjkjkgjkgjkgjkgjkgkgjkhjkhkhjk",
        "puntuacion": 5,
        "hora": "2024-12-03 13:48:26"
    },
    {
        "nombre": "",
        "puntuacion": 5,
        "hora": "2024-12-03 13:48:30"
    },
    {
        "nombre": "jjkjklaklsaklsajklsadjsd",
        "puntuacion": -5,
        "hora": "2024-12-03 11:22:58"
    },
    {
        "nombre": null,
        "puntuacion": -5,
        "hora": "2024-12-03 11:23:02"
    }
]